speedtest_monitor/main.py
speedtest_monitor/plot.py
speedtest_monitor/speed_utils.py
speedtest_monitor/time_utils.py
speedtest_monitor-0.0.2.dist-info/METADATA
speedtest_monitor-0.0.2.dist-info/WHEEL
speedtest_monitor-0.0.2.dist-info/entry_points.txt
speedtest_monitor-0.0.2.dist-info/top_level.txt
speedtest_monitor-0.0.2.dist-info/RECORD
