Metadata-Version: 2.1
Name: speedtest-monitor
Version: 0.0.2
Summary: Monitor your speed test automatically using speedtest.net
Home-page: https://github.com/mohammedi-haroune/speedtest-monitor
Author: Haroune Mohammedi
Author-email: mohammedi.haroun@gmail.com
License: MIT
Platform: UNKNOWN
Requires-Dist: pandas (~=1.2.2)
Requires-Dist: matplotlib (~=3.3.4)
Requires-Dist: numpy (~=1.20.1)
Requires-Dist: speedtest-cli (~=2.1.2)
Requires-Dist: PyQt5 (~=5.15.2)
Requires-Dist: python-crontab (~=2.5.1)
